jsonlang.py
jsonlang-0.1.2.dist-info/DESCRIPTION.rst
jsonlang-0.1.2.dist-info/METADATA
jsonlang-0.1.2.dist-info/RECORD
jsonlang-0.1.2.dist-info/WHEEL
jsonlang-0.1.2.dist-info/entry_points.txt
jsonlang-0.1.2.dist-info/metadata.json
jsonlang-0.1.2.dist-info/top_level.txt
