Metadata-Version: 2.0
Name: jsonlang
Version: 0.1.2
Summary: JSONLang Python Implement.
Home-page: https://github.com/soasme/jsonlang
Author: Ju Lin
Author-email: soasme@gmail.com
License: MIT
Keywords: jsonlang
Platform: UNKNOWN
Classifier: Development Status :: 2 - Pre-Alpha
Classifier: Intended Audience :: Developers
Classifier: Natural Language :: English
Classifier: Programming Language :: Python :: 2
Classifier: Programming Language :: Python :: 2.6
Classifier: Programming Language :: Python :: 2.7
Classifier: Programming Language :: Python :: 3
Classifier: Programming Language :: Python :: 3.3
Classifier: Programming Language :: Python :: 3.4
Classifier: Programming Language :: Python :: 3.5
